brdr/__init__.py
brdr/aligner.py
brdr/configs.py
brdr/constants.py
brdr/enums.py
brdr/feature_data.py
brdr/geometry_utils.py
brdr/loader.py
brdr/logger.py
brdr/processor.py
brdr/topo_utils.py
brdr/typings.py
brdr/utils.py
brdr/viz.py
brdr/be/__init__.py
brdr/be/be.py
brdr/be/constants.py
brdr/be/grb/__init__.py
brdr/be/grb/analysis.py
brdr/be/grb/constants.py
brdr/be/grb/enums.py
brdr/be/grb/grb.py
brdr/be/grb/loader.py
brdr/be/grb/utils.py
brdr/be/oe/__init__.py
brdr/be/oe/constants.py
brdr/be/oe/enums.py
brdr/be/oe/loader.py
brdr/be/oe/utils.py
brdr/nl/__init__.py
brdr/nl/constants.py
brdr/nl/enums.py
brdr/nl/loader.py
brdr/osm/__init__.py
brdr/osm/constants.py
brdr/osm/loader.py
brdr-0.15.3.dist-info/METADATA
brdr-0.15.3.dist-info/WHEEL
brdr-0.15.3.dist-info/licenses/LICENSE
brdr-0.15.3.dist-info/RECORD
