Metadata-Version: 2.4
Name: brdr
Version: 0.15.3
Summary: BRDR - a Python library to assist in realigning (multi-)polygons (OGC Simple Features) to reference borders 
Project-URL: Documentation, https://github.com/OnroerendErfgoed/brdr/blob/main/README.md
Project-URL: Repository, https://github.com/OnroerendErfgoed/brdr
Project-URL: Issues, https://github.com/OnroerendErfgoed/brdr/issues
Author-email: Karel Dieussaert <karel.dieussaert@vlaanderen.be>, Emrys Roef <emrys.roef@vlaanderen.be>
Maintainer-email: Emrys Roef <emrys.roef@vlaanderen.be>, Koen Van Daele <koen.vandaele@vlaanderen.be>, Vermeyen Maarten <maarten.vermeyen@vlaanderen.be>
License: MIT License
License-File: LICENSE
Classifier: Development Status :: 3 - Alpha
Classifier: License :: OSI Approved :: MIT License
Classifier: Operating System :: OS Independent
Classifier: Programming Language :: Python :: 3.11
Classifier: Programming Language :: Python :: 3.12
Classifier: Programming Language :: Python :: 3.13
Classifier: Programming Language :: Python :: 3.14
Classifier: Topic :: Scientific/Engineering :: GIS
Requires-Python: >=3.10
Requires-Dist: geojson~=3.2
Requires-Dist: geopandas~=1.1
Requires-Dist: networkx~=3.6
Requires-Dist: osmnx~=2.0
Requires-Dist: pyproj~=3.7
Requires-Dist: requests~=2.32
Requires-Dist: shapely~=2.1
Requires-Dist: topojson~=1.10
Provides-Extra: dev
Requires-Dist: black~=25.12; extra == 'dev'
Requires-Dist: flake8==7.1.1; extra == 'dev'
Requires-Dist: hatchling~=1.28; extra == 'dev'
Requires-Dist: matplotlib~=3.10; extra == 'dev'
Requires-Dist: mypy~=1.14; extra == 'dev'
Requires-Dist: pillow~=12.0; extra == 'dev'
Requires-Dist: pip-tools~=7.5; extra == 'dev'
Requires-Dist: pyogrio~=0.12; extra == 'dev'
Requires-Dist: pytest-cov==6.0.0; extra == 'dev'
Requires-Dist: pytest==8.3.4; extra == 'dev'
Requires-Dist: responses==0.25.6; extra == 'dev'
Requires-Dist: toml==0.10.2; extra == 'dev'
Requires-Dist: types-requests~=2.32; extra == 'dev'
Provides-Extra: test
Requires-Dist: pytest-cov==6.0.0; extra == 'test'
Requires-Dist: pytest==8.3.4; extra == 'test'
Requires-Dist: responses==0.25.6; extra == 'test'
Requires-Dist: toml==0.10.2; extra == 'test'
Provides-Extra: viz
Requires-Dist: matplotlib~=3.10; extra == 'viz'
Requires-Dist: pillow~=12.0; extra == 'viz'
